mfawesome/__init__.py
mfawesome/__main__.py
mfawesome/config.py
mfawesome/countdownbars.py
mfawesome/data/__init__.py
mfawesome/data/ntpservers.yaml
mfawesome/exception.py
mfawesome/exec_mfawesome.py
mfawesome/logutils.py
mfawesome/mfa_secrets.py
mfawesome/ntptime.py
mfawesome/qrcodes.py
mfawesome/totp.py
mfawesome/utils.py
mfawesome_tests/__init__.py
mfawesome_tests/pyproject.toml
mfawesome_tests/test_mfawesome.py
mfawesome-0.1.76.dist-info/LICENSE
mfawesome-0.1.76.dist-info/METADATA
mfawesome-0.1.76.dist-info/WHEEL
mfawesome-0.1.76.dist-info/entry_points.txt
mfawesome-0.1.76.dist-info/RECORD
