Metadata-Version: 2.3
Name: mfawesome
Version: 0.1.76
Summary: CLI Multi-Factor Authenticator Tool
Author: Rob Milloy
Author-email: rob@milloy.net
Requires-Python: >=3.10,<4.0
Classifier: Development Status :: 5 - Production/Stable
Classifier: Environment :: Console
Classifier: Framework :: Jupyter
Classifier: Intended Audience :: Developers
Classifier: Intended Audience :: End Users/Desktop
Classifier: Intended Audience :: System Administrators
Classifier: License :: Freeware
Classifier: Natural Language :: English
Classifier: Operating System :: OS Independent
Classifier: Programming Language :: Python :: 3
Classifier: Programming Language :: Python :: 3.10
Classifier: Programming Language :: Python :: 3.11
Classifier: Programming Language :: Python :: 3.12
Classifier: Programming Language :: Python :: 3.13
Classifier: Topic :: Desktop Environment
Classifier: Topic :: Internet
Classifier: Topic :: Internet :: WWW/HTTP
Classifier: Topic :: Internet :: WWW/HTTP :: Session
Classifier: Topic :: Office/Business
Classifier: Topic :: Security
Classifier: Topic :: Security :: Cryptography
Classifier: Topic :: System :: Systems Administration
Classifier: Topic :: Utilities
Provides-Extra: all
Requires-Dist: PyYAML
Requires-Dist: cryptography (>=42.0)
Requires-Dist: numpy
Requires-Dist: opencv-contrib-python-headless (>=4.5)
Requires-Dist: protobuf
Requires-Dist: qrcode[pil] (>=7.4)
Requires-Dist: rich
